allokation/__init__.py
allokation/allokate.py
allokation/utils.py
allokation-0.1.0.dist-info/LICENSE
allokation-0.1.0.dist-info/METADATA
allokation-0.1.0.dist-info/WHEEL
allokation-0.1.0.dist-info/top_level.txt
allokation-0.1.0.dist-info/RECORD
