Metadata-Version: 2.1
Name: allokation
Version: 0.1.0
Summary: 
Home-page: https://github.com/capaci/allokation
Author: Rafael Capaci
Author-email: rafaelcapacipereira@gmail.com
License: MIT License
Download-URL: https://github.com/capaci/allokation/archive/0.1.0.tar.gz
Keywords: finance,stocks,portfolio allocation
Platform: UNKNOWN
Classifier: Development Status :: 3 - Alpha
Classifier: Intended Audience :: Developers
Classifier: Intended Audience :: Financial and Insurance Industry
Classifier: Intended Audience :: Other Audience
Classifier: Topic :: Office/Business :: Financial :: Investment
Classifier: License :: OSI Approved :: MIT License
Classifier: Programming Language :: Python :: 3.8
Requires-Python: >=3.8
Requires-Dist: pandas-datareader (==0.9.0)
Requires-Dist: pandas (==1.1.1)
